ec2list/__init__.py
ec2list/ec2list.py
ec2list-1.1.1.dist-info/DESCRIPTION.rst
ec2list-1.1.1.dist-info/entry_points.txt
ec2list-1.1.1.dist-info/METADATA
ec2list-1.1.1.dist-info/metadata.json
ec2list-1.1.1.dist-info/RECORD
ec2list-1.1.1.dist-info/top_level.txt
ec2list-1.1.1.dist-info/WHEEL
ec2list-1.1.1.dist-info/zip-safe
